gradio_simpletextextractfrompdf/SimpleTextExtractFromPDF.py
gradio_simpletextextractfrompdf/SimpleTextExtractFromPDF.pyi
gradio_simpletextextractfrompdf/__init__.py
gradio_simpletextextractfrompdf/templates/component/index.js
gradio_simpletextextractfrompdf/templates/component/style.css
gradio_simpletextextractfrompdf/templates/example/index.js
gradio_simpletextextractfrompdf/templates/example/style.css
gradio_simpletextextractfrompdf-0.0.4.dist-info/METADATA
gradio_simpletextextractfrompdf-0.0.4.dist-info/WHEEL
gradio_simpletextextractfrompdf-0.0.4.dist-info/RECORD
