Metadata-Version: 2.4
Name: gradio_simpletextextractfrompdf
Version: 0.0.4
Summary: Extracts text from pdf documents
Author-email: HuggyMonkey <huggy.monkey00@gmail.com>
License-Expression: Apache-2.0
Keywords: gradio-custom-component,gradio-template-Fallback,pdf to string,simple text extraction,text extraction from pdf
Classifier: Development Status :: 3 - Alpha
Classifier: Operating System :: OS Independent
Classifier: Programming Language :: Python :: 3
Classifier: Programming Language :: Python :: 3 :: Only
Classifier: Programming Language :: Python :: 3.8
Classifier: Programming Language :: Python :: 3.9
Classifier: Programming Language :: Python :: 3.10
Classifier: Programming Language :: Python :: 3.11
Classifier: Topic :: Scientific/Engineering
Classifier: Topic :: Scientific/Engineering :: Artificial Intelligence
Classifier: Topic :: Scientific/Engineering :: Visualization
Requires-Python: >=3.10
Requires-Dist: gradio<6.0,>=4.0
Provides-Extra: dev
Requires-Dist: build; extra == 'dev'
Requires-Dist: twine; extra == 'dev'
